LICENSE
sugarjazy/__init__.py
sugarjazy/cli.py
sugarjazy-0.2.0.dist-info/entry_points.txt
sugarjazy-0.2.0.dist-info/LICENSE
sugarjazy-0.2.0.dist-info/WHEEL
sugarjazy-0.2.0.dist-info/METADATA
sugarjazy-0.2.0.dist-info/RECORD
